{
  "users": [
    {
      "name": "Andrej",
      "surname": "Trailovic",
      "email": "trajce@gmail.com",
      "password": "mrk1234567",
      "type":"user",
      "id": "b2e8"
    },
    {
      "name": "Jovan",
      "surname": "Vukadinovic",
      "email": "joca@gmail.com",
      "password": "smrk123",
      "type":"user",
      "id": "464e"
    },
    {
      "name": "Admin",
      "surname": "Admin",
      "email": "Admin@gmail.com",
      "password": "Admin123",
      "type":"admin",
      "id": "1"
    }
   
  ],
  "products":[{
    "name":"White-Bread",
    "category":"Breads",
    "price":"60"
  },
{
  "name":"Rye-Bread",
   "category":"Breads",
    "price":"90"
},
{
  "name":"Corn-Bread",
   "category":"Breads",
    "price":"85"
},
{
  "name":"Wholemeal",
   "category":"Breads",
    "price":"100"
},
{
  "name":"Meat",
  "category":"Burek",
  "price":"650"
},
{
"name":"Cheese",
 "category":"Burek",
  "price":"450"
},
{
  "name":"Bagel",
  "category":"Pastries",
  "price":"45"
},
{
"name":"Croissant",
 "category":"Pastries",
  "price":"100  "
}


]

  
}